mfsetup/__init__.py
mfsetup/_version.py
mfsetup/bcs.py
mfsetup/checks.py
mfsetup/config.py
mfsetup/discretization.py
mfsetup/equality.py
mfsetup/evaporation.py
mfsetup/fileio.py
mfsetup/grid.py
mfsetup/ic.py
mfsetup/interpolate.py
mfsetup/lakes.py
mfsetup/mf5to6.py
mfsetup/mf6_defaults.yml
mfsetup/mf6model.py
mfsetup/mfmodel.py
mfsetup/mfnwt_defaults.yml
mfsetup/mfnwtmodel.py
mfsetup/model_version.py
mfsetup/mover.py
mfsetup/obs.py
mfsetup/oc.py
mfsetup/sourcedata.py
mfsetup/sourcemodel.py
mfsetup/tdis.py
mfsetup/testing.py
mfsetup/tmr.py
mfsetup/units.py
mfsetup/utils.py
mfsetup/wateruse.py
mfsetup/wells.py
mfsetup/zbud.py
mfsetup/tests/__init__.py
mfsetup/tests/conftest.py
mfsetup/tests/plot.py
mfsetup/tests/test_bcs.py
mfsetup/tests/test_config.py
mfsetup/tests/test_discretization.py
mfsetup/tests/test_equality.py
mfsetup/tests/test_evaporation.py
mfsetup/tests/test_fileio.py
mfsetup/tests/test_get_data_from_parent.py
mfsetup/tests/test_get_model_version.py
mfsetup/tests/test_grid.py
mfsetup/tests/test_ic.py
mfsetup/tests/test_import.py
mfsetup/tests/test_interpolation.py
mfsetup/tests/test_lakes.py
mfsetup/tests/test_lgr.py
mfsetup/tests/test_mf5to6.py
mfsetup/tests/test_mf6_shellmound.py
mfsetup/tests/test_mf6_shellmound_mixed_layers.py
mfsetup/tests/test_mf6_shellmound_rot_grid.py
mfsetup/tests/test_mf6_tmr_shellmound.py
mfsetup/tests/test_mover.py
mfsetup/tests/test_notebooks.py
mfsetup/tests/test_obs.py
mfsetup/tests/test_oc.py
mfsetup/tests/test_pfl_mfnwt_inset.py
mfsetup/tests/test_pleasant_mf6_inset.py
mfsetup/tests/test_pleasant_mfnwt_inset.py
mfsetup/tests/test_solver_setup.py
mfsetup/tests/test_sourcedata.py
mfsetup/tests/test_tdis.py
mfsetup/tests/test_testing.py
mfsetup/tests/test_tmr.py
mfsetup/tests/test_units.py
mfsetup/tests/test_usage.py
mfsetup/tests/test_utils.py
mfsetup/tests/test_wateruse.py
mfsetup/tests/test_wells.py
modflow_setup-0.7.0.dist-info/licenses/LICENSE.md
modflow_setup-0.7.0.dist-info/METADATA
modflow_setup-0.7.0.dist-info/WHEEL
modflow_setup-0.7.0.dist-info/top_level.txt
modflow_setup-0.7.0.dist-info/RECORD
